libcolgraph/Graph.cpp
libcolgraph/__init__.py
libcolgraph/GraphTemplates.h
libcolgraph/Graph.h
libcolgraph/libcolgraph.i
libcolgraph/Vertex.cpp
libcolgraph/__main__.py
libcolgraph/_libcolgraph.cpython-35m-x86_64-linux-gnu.so
libcolgraph/libcolgraph_wrap.cpp
libcolgraph/Vertex.h
libcolgraph/libcolgraph.py
libcolgraph/discovery/__init__.py
libcolgraph/conjecture/__init__.py
libcolgraph/graphics/__init__.py
libcolgraph/graphics/graphics.py
libcolgraph/swigsrc/template_defs.i
libcolgraph/swigsrc/wrapped_exceptions.i
libcolgraph/swigsrc/pyoverrides.i
libcolgraph/swigsrc/docs.i
libcolgraph/swigsrc/cpp_inline.i
libcolgraph/web/__init__.py
libcolgraph/web/web.py
libcolgraph/web/__main__.py
libcolgraph/web/app.py
libcolgraph/web/templates/index.html
libcolgraph/web/templates/graphcontainer.html
libcolgraph/web/templates/grid.html
libcolgraph/web/static/grid.css
libcolgraph/web/static/colgraphweb.js
libcolgraph/web/static/favicon.ico
libcolgraph/web/static/src/vis.css
libcolgraph/web/static/src/vis-network.min.js
libcolgraph/web/static/src/jquery.min.js
libcolgraph-0.0.7.dist-info/RECORD
libcolgraph-0.0.7.dist-info/LICENSE
libcolgraph-0.0.7.dist-info/entry_points.txt
libcolgraph-0.0.7.dist-info/WHEEL
libcolgraph-0.0.7.dist-info/METADATA
libcolgraph-0.0.7.dist-info/top_level.txt
