Metadata-Version: 2.1
Name: libcolgraph
Version: 0.0.7
Summary: this library provides support to construct graphs and their coloring graphs. a coloring graph is a metagraph representing all the valid colorings of a graph. each vertex of a coloring graph represents a coloring of the base graph.
Home-page: https://github.com/aalok-sathe/libcolgraph.git
Author: Coloring Graphs lab, Univeristy of Richmond
Author-email: aalok.sathe@richmond.edu
License: LGPL-3
Platform: UNKNOWN
Classifier: Intended Audience :: Education
Classifier: Intended Audience :: Science/Research
Classifier: License :: OSI Approved :: GNU Lesser General Public License v3 or later (LGPLv3+)
Classifier: Programming Language :: Python :: 3.5
Classifier: Topic :: Software Development :: Libraries :: Python Modules
Requires-Python: >=3.4
Requires-Dist: coloredlogs
Requires-Dist: matplotlib
Requires-Dist: cycler
Requires-Dist: Flask
Requires-Dist: networkx
Requires-Dist: PySimpleGUI
Requires-Dist: pdoc3
